fastapi_jwt_authlib/__init__.py
fastapi_jwt_authlib/auth.py
fastapi_jwt_authlib/depends.py
fastapi_jwt_authlib/exception.py
fastapi_jwt_authlib/helper.py
fastapi_jwt_authlib-0.8.0.dist-info/LICENSE
fastapi_jwt_authlib-0.8.0.dist-info/METADATA
fastapi_jwt_authlib-0.8.0.dist-info/WHEEL
fastapi_jwt_authlib-0.8.0.dist-info/RECORD
