Metadata-Version: 2.3
Name: fastapi-jwt-authlib
Version: 0.8.0
Summary: A FastAPI JWT authentication library
License: MIT
Author: kovalew.vladimir
Author-email: kovalew.vladimir@gmail.com
Requires-Python: >=3.12,<4.0
Classifier: License :: OSI Approved :: MIT License
Classifier: Programming Language :: Python :: 3
Classifier: Programming Language :: Python :: 3.12
Classifier: Programming Language :: Python :: 3.13
Requires-Dist: fastapi (>=0.114.0,<1.0.0)
Requires-Dist: pyjwt (==2.9.0)
Project-URL: Homepage, https://github.com/kovalewvladimir/fastapi-jwt-authlib
Project-URL: Repository, https://github.com/kovalewvladimir/fastapi-jwt-authlib
